mycalc/calculator.py
changyun1385-0.0.1.dist-info/METADATA
changyun1385-0.0.1.dist-info/WHEEL
changyun1385-0.0.1.dist-info/top_level.txt
changyun1385-0.0.1.dist-info/RECORD
