Metadata-Version: 2.1
Name: changyun1385
Version: 0.0.1
Summary: my calculator
Home-page: https://github.com/changyun1385/mycalc
Download-URL: https://github.com/changyun1385/mycalc
Author: changyun
License: UNKNOWN
Platform: UNKNOWN
Classifier: Programming Language :: Python :: 3
